ratatoskr/__init__.py
ratatoskr_py-0.0.1.dist-info/METADATA
ratatoskr_py-0.0.1.dist-info/WHEEL
ratatoskr_py-0.0.1.dist-info/licenses/LICENSE
ratatoskr_py-0.0.1.dist-info/RECORD
